ninjar/__init__.py
ninjar/cmds.py
ninjar/expr.py
ninjar/main.py
ninjar/ninja.py
ninjar/py.typed
ninjar/shell.py
ninjar/writeln.py
ninjar-1.0.3.dist-info/METADATA
ninjar-1.0.3.dist-info/WHEEL
ninjar-1.0.3.dist-info/licenses/LICENSE
ninjar-1.0.3.dist-info/RECORD
