Metadata-Version: 2.3
Name: ninjar
Version: 1.0.3
Summary: A small ninjar build script generator framework.
Project-URL: Repository, https://github.com/XiangYyang/ninjar.git
Author-email: XiangYang <hinata.hoshino@foxmail.com>
License: The Clear BSD License
License-File: LICENSE
Keywords: ninjar generator
Classifier: License :: OSI Approved :: BSD License
Classifier: Operating System :: OS Independent
Classifier: Programming Language :: Python :: 3.11
Classifier: Programming Language :: Python :: 3.12
Classifier: Programming Language :: Python :: Implementation :: CPython
Classifier: Typing :: Typed
Requires-Python: >=3.11
Requires-Dist: colorama>=0.4.5
